atelier_facture/__init__.py
atelier_facture/atelier_facture.py
atelier_facture/etapes/__init__.py
atelier_facture/etapes/consolidation.py
atelier_facture/etapes/extraction.py
atelier_facture/etapes/formatage.py
atelier_facture/etapes/fusion.py
atelier_facture/scripts_divers/indiv_export_facturx.py
atelier_facture/scripts_divers/verif_xslx.py
atelier_facture/utils/__init__.py
atelier_facture/utils/file_naming.py
atelier_facture/utils/logger_config.py
atelier_facture/utils/mpl.py
atelier_facture/utils/pdf_utils.py
atelier_facture/utils/pedagogie.py
atelier_facture-1.1.2.dist-info/LICENSE
atelier_facture-1.1.2.dist-info/METADATA
atelier_facture-1.1.2.dist-info/WHEEL
atelier_facture-1.1.2.dist-info/entry_points.txt
atelier_facture-1.1.2.dist-info/RECORD
