Metadata-Version: 2.1
Name: atelier-facture
Version: 1.1.2
Summary: 
Home-page: https://github.com/Virgile-Dauge/formatage_multi_site
License: GPLv3
Author: Virgile
Author-email: virgile.dauge@pm.me
Requires-Python: >=3.10,<4.0
Classifier: License :: Other/Proprietary License
Classifier: Programming Language :: Python :: 3
Classifier: Programming Language :: Python :: 3.10
Classifier: Programming Language :: Python :: 3.11
Classifier: Programming Language :: Python :: 3.12
Classifier: Programming Language :: Python :: 3.13
Requires-Dist: facturix (>=1.0.4,<2.0.0)
Requires-Dist: matplotlib (>=3.9.4,<4.0.0)
Requires-Dist: pandas (>=2.2.3,<3.0.0)
Requires-Dist: pymupdf (>=1.25.1,<2.0.0)
Requires-Dist: rich (>=13.9.4,<14.0.0)
Project-URL: Repository, https://github.com/Virgile-Dauge/formatage_multi_site
